myuplink/__init__.py
myuplink/api.py
myuplink/auth.py
myuplink/auth_abstract.py
myuplink/models.py
myuplink/names.py
myuplink/py.typed
myuplink-0.6.0.dist-info/METADATA
myuplink-0.6.0.dist-info/WHEEL
myuplink-0.6.0.dist-info/top_level.txt
myuplink-0.6.0.dist-info/RECORD
